kraken_sample/__init__.py
kraken_sample/class_kraken_sample.py
kraken_sample/class_kraken_samples.py
kraken_sample/flask_routes.py
kraken_sample/kraken_sample.py
kraken_sample/helpers/__init__.py
kraken_sample/helpers/json.py
kraken_sample/helpers/things.py
kraken_sample/records/__init__.py
kraken_sample/records/action.py
kraken_sample/records/aggregateRating.py
kraken_sample/records/article.py
kraken_sample/records/brand.py
kraken_sample/records/imageObject.py
kraken_sample/records/invoice.py
kraken_sample/records/lorem.py
kraken_sample/records/offer.py
kraken_sample/records/order.py
kraken_sample/records/order_item.py
kraken_sample/records/organization.py
kraken_sample/records/person.py
kraken_sample/records/postalAddress.py
kraken_sample/records/priceSpecification.py
kraken_sample/records/product.py
kraken_sample/records/quantitativeValue.py
kraken_sample/records/rating.py
kraken_sample/records/records.py
kraken_sample/records/review.py
kraken_sample/records/thing.py
kraken_sample/records/website.py
kraken_sample-0.0.1.dist-info/LICENSE.txt
kraken_sample-0.0.1.dist-info/METADATA
kraken_sample-0.0.1.dist-info/WHEEL
kraken_sample-0.0.1.dist-info/top_level.txt
kraken_sample-0.0.1.dist-info/RECORD
